jinja_partials/__init__.py
jinja_partials-0.2.0.dist-info/LICENSE
jinja_partials-0.2.0.dist-info/METADATA
jinja_partials-0.2.0.dist-info/WHEEL
jinja_partials-0.2.0.dist-info/top_level.txt
jinja_partials-0.2.0.dist-info/RECORD
