Metadata-Version: 2.1
Name: jinja_partials
Version: 0.2.0
Summary: Simple reuse of partial HTML page templates in the Jinja template language for Python web frameworks.
Home-page: https://github.com/mikeckennedy/jinja_partials
Author: Michael Kennedy
Author-email: michael@talkpython.fm
License: MIT
Classifier: Development Status :: 2 - Pre-Alpha
Classifier: License :: OSI Approved :: MIT License
Classifier: Programming Language :: Python
Classifier: Programming Language :: Python :: 3
Classifier: Programming Language :: Python :: 3.6
Classifier: Programming Language :: Python :: 3.7
Classifier: Programming Language :: Python :: 3.8
Classifier: Programming Language :: Python :: 3.9
Classifier: Programming Language :: Python :: 3.10
License-File: LICENSE
Requires-Dist: jinja2
